README.md
setup.cfg
setup.py
outliers_101703013_2.egg-info/PKG-INFO
outliers_101703013_2.egg-info/SOURCES.txt
outliers_101703013_2.egg-info/dependency_links.txt
outliers_101703013_2.egg-info/top_level.txt
outliers_101703013_project_2/__init__.py
outliers_101703013_project_2/outliers_101703013_2.py