Metadata-Version: 2.1
Name: outliers-101703013-2
Version: 0.0.2
Summary: Outliers Removal
Home-page: https://github.com/aayush03041/outliers_101703013
Author: Aayush Singla
Author-email: singlaaayush0@gmail.com
License: UNKNOWN
Download-URL: https://github.com/aayush03041/outliers_101703013/archive/v_01.tar.gz
Platform: UNKNOWN
Classifier: Programming Language :: Python :: 3
Classifier: License :: OSI Approved :: MIT License
Classifier: Operating System :: OS Independent
Requires-Python: >=3.7
